{
  "generated_at": "2026-06-12T07:11:48.395744+08:00",
  "total_titles_processed": 613,
  "failed_sources": [],
  "trends": [
    {
      "keyword_group": "特朗普",
      "match_count": 38,
      "titles": [
        {
          "title": "国际油价飙升！特朗普：今晚将重创伊朗，“在不久的将来”将占领哈尔克岛",
          "url": "https://wallstreetcn.com/articles/3774439",
          "source": "华尔街见闻",
          "ranks": [
            3,
            2
          ],
          "is_new": false,
          "appearance_count": 4,
          "time_info": "[00时36分 ~ 07时11分]"
        },
        {
          "title": "据华尔街日报：特朗普与盟友正制定计划以“抹除”弹劾记录。",
          "url": "https://flash.jin10.com/detail/20260612070155257800",
          "source": "金十数据",
          "ranks": [
            1
          ],
          "is_new": true,
          "appearance_count": 1,
          "time_info": "07时11分"
        },
        {
          "title": "美债价格于纽约中午短线飙涨，特朗普取消对伊朗的后续袭击计划",
          "url": "https://wallstreetcn.com/livenews/3118414",
          "source": "华尔街见闻-快讯",
          "ranks": [
            1
          ],
          "is_new": false,
          "appearance_count": 1,
          "time_info": "05时35分"
        },
        {
          "title": "特朗普称取消打击伊朗行动",
          "url": "https://news.ifeng.com/c/8tsig3GUtRk",
          "source": "凤凰网",
          "ranks": [
            2
          ],
          "is_new": true,
          "appearance_count": 1,
          "time_info": "07时11分"
        },
        {
          "title": "特朗普称美伊协议进入最后定稿阶段，有望本周末签署",
          "url": "https://news.ifeng.com/c/8tso5G96e80",
          "source": "凤凰网",
          "ranks": [
            3
          ],
          "is_new": true,
          "appearance_count": 1,
          "time_info": "07时11分"
        },
        {
          "title": "美国总统特朗普谈及伊朗问题，声称：基本完成。 我们得到了我们想要的一切。",
          "url": "https://wallstreetcn.com/livenews/3118442",
          "source": "华尔街见闻-快讯",
          "ranks": [
            4
          ],
          "is_new": true,
          "appearance_count": 1,
          "time_info": "07时11分"
        },
        {
          "title": "不断强调“接近协议”，如今又开启“强硬打击”，特朗普能打破美伊“不战不和”僵局吗？",
          "url": "https://wallstreetcn.com/articles/3774371",
          "source": "华尔街见闻",
          "ranks": [
            8,
            7,
            6
          ],
          "is_new": false,
          "appearance_count": 4,
          "time_info": "[00时36分 ~ 07时11分]"
        },
        {
          "title": "特朗普称自己“被当成傻瓜戏耍”，到底发生了什么？",
          "url": "https://news.ifeng.com/c/8tsLNrnEAQM",
          "source": "凤凰网",
          "ranks": [
            12
          ],
          "is_new": false,
          "appearance_count": 4,
          "time_info": "[00时36分 ~ 07时11分]"
        },
        {
          "title": "特朗普称取消打击伊朗行动",
          "url": "https://s.weibo.com/weibo?q=%23%E7%89%B9%E6%9C%97%E6%99%AE%E7%A7%B0%E5%8F%96%E6%B6%88%E6%89%93%E5%87%BB%E4%BC%8A%E6%9C%97%E8%A1%8C%E5%8A%A8%23&t=31&band_rank=9&Refer=top",
          "source": "微博",
          "ranks": [
            9,
            7
          ],
          "is_new": false,
          "appearance_count": 2,
          "time_info": "[05时35分 ~ 07时11分]"
        },
        {
          "title": "市场消息：卡塔尔埃米尔与美国总统特朗普通话。",
          "url": "https://flash.jin10.com/detail/20260612030527728800",
          "source": "金十数据",
          "ranks": [
            8
          ],
          "is_new": false,
          "appearance_count": 1,
          "time_info": "03时24分"
        },
        {
          "title": "特朗普叫停对伊朗打击！称“未来几天”签和平协议，伊朗回应：还没结论！",
          "url": "https://flash.jin10.com/detail/20260612064649190800",
          "source": "金十数据",
          "ranks": [
            8
          ],
          "is_new": true,
          "appearance_count": 1,
          "time_info": "07时11分"
        },
        {
          "title": "金十提示：美国总统特朗普将此前取消打击伊朗的帖子置顶。",
          "url": "https://flash.jin10.com/detail/20260612064451567800",
          "source": "金十数据",
          "ranks": [
            10
          ],
          "is_new": true,
          "appearance_count": 1,
          "time_info": "07时11分"
        },
        {
          "title": "特朗普政府将就法官叫停10万美元H-1B签证费的裁决提起上诉",
          "url": "https://wallstreetcn.com/livenews/3118297",
          "source": "华尔街见闻-快讯",
          "ranks": [
            11
          ],
          "is_new": false,
          "appearance_count": 1,
          "time_info": "00时36分"
        },
        {
          "title": "彭博美元指数创逾1个月最大跌幅，特朗普暗示美伊协议即将达成",
          "url": "https://wallstreetcn.com/livenews/3118400",
          "source": "华尔街见闻-快讯",
          "ranks": [
            13
          ],
          "is_new": false,
          "appearance_count": 1,
          "time_info": "05时35分"
        },
        {
          "title": "特朗普称伊朗各方均已批准美伊协议",
          "url": "https://flash.jin10.com/detail/20260612042328842800",
          "source": "金十数据",
          "ranks": [
            15
          ],
          "is_new": false,
          "appearance_count": 1,
          "time_info": "05时35分"
        },
        {
          "title": "以方称特朗普承诺美伊协议将包括移除伊朗浓缩铀等内容",
          "url": "https://wallstreetcn.com/livenews/3118398",
          "source": "华尔街见闻-快讯",
          "ranks": [
            15
          ],
          "is_new": false,
          "appearance_count": 1,
          "time_info": "05时35分"
        },
        {
          "title": "特朗普拒设协议截止日期：设了你们又会说我没按期完成",
          "url": "https://flash.jin10.com/detail/20260612042246303800",
          "source": "金十数据",
          "ranks": [
            16
          ],
          "is_new": false,
          "appearance_count": 1,
          "time_info": "05时35分"
        },
        {
          "title": "金十提示：美国总统特朗普结束白宫讲话。",
          "url": "https://flash.jin10.com/detail/20260612042139765800",
          "source": "金十数据",
          "ranks": [
            17
          ],
          "is_new": false,
          "appearance_count": 1,
          "time_info": "05时35分"
        },
        {
          "title": "据以色列第12频道记者报道，伊朗否认存在任何协议。以色列方面表示，并不存在这样的协议。 另据以色列i24News报道，两名以色列官员称，对特朗普的声明感到意外，需要等待伊朗方面公布相关内容，才能判断这一说法是否准确。",
          "url": "https://wallstreetcn.com/livenews/3118352",
          "source": "华尔街见闻-快讯",
          "ranks": [
            17
          ],
          "is_new": false,
          "appearance_count": 1,
          "time_info": "03时24分"
        },
        {
          "title": "伊媒嘲讽特朗普再次TACO",
          "url": "https://flash.jin10.com/detail/20260612024640276800",
          "source": "金十数据",
          "ranks": [
            18
          ],
          "is_new": false,
          "appearance_count": 1,
          "time_info": "03时24分"
        },
        {
          "title": "美国总统特朗普：考虑对肥料市场提供某种形式的帮助。",
          "url": "https://flash.jin10.com/detail/20260612041838711800",
          "source": "金十数据",
          "ranks": [
            19
          ],
          "is_new": false,
          "appearance_count": 1,
          "time_info": "05时35分"
        },
        {
          "title": "特朗普提名原SEC主席为美国国家情报总监",
          "url": "https://wallstreetcn.com/livenews/3118350",
          "source": "华尔街见闻-快讯",
          "ranks": [
            19
          ],
          "is_new": false,
          "appearance_count": 1,
          "time_info": "03时24分"
        },
        {
          "title": "【特朗普称伊朗各方均已批准美伊协议】美国总统特朗普谈及美伊协议称，据他了解，伊朗最高领袖已同意该协议，伊朗各方均已批准该协议。他还表示，这是一份非常有力、非常详尽的谅解备忘录。特朗普还称，伊朗将不会拥有核武器。特朗普表示，一旦签署谅解备忘录，霍尔木兹海峡将立即开放。他还称，哈尔克岛行动不在考虑之列。 此前，一名接近伊朗谈判团队的知情人士称，伊朗“尚未批准任何与美国达成的初步谅解备忘录文本”。（央视）",
          "url": "https://wallstreetcn.com/livenews/3118394",
          "source": "华尔街见闻-快讯",
          "ranks": [
            19
          ],
          "is_new": false,
          "appearance_count": 1,
          "time_info": "05时35分"
        },
        {
          "title": "美国总统特朗普：伊朗协议“已经基本敲定”。（纽约邮报）",
          "url": "https://wallstreetcn.com/livenews/3118348",
          "source": "华尔街见闻-快讯",
          "ranks": [
            20
          ],
          "is_new": false,
          "appearance_count": 1,
          "time_info": "03时24分"
        },
        {
          "title": "特朗普表示相信伊朗最高领袖已批准美伊协议",
          "url": "https://wallstreetcn.com/livenews/3118393",
          "source": "华尔街见闻-快讯",
          "ranks": [
            20
          ],
          "is_new": false,
          "appearance_count": 1,
          "time_info": "05时35分"
        },
        {
          "title": "以色列：特朗普承诺伊朗将限制导弹生产及停止地区支持",
          "url": "https://flash.jin10.com/detail/20260612041456892800",
          "source": "金十数据",
          "ranks": [
            21
          ],
          "is_new": false,
          "appearance_count": 1,
          "time_info": "05时35分"
        },
        {
          "title": "美媒：特朗普不满对伊打击“反响冷淡” 认为伊朗和媒体都没当回事",
          "url": "https://flash.jin10.com/detail/20260611233949311800",
          "source": "金十数据",
          "ranks": [
            22
          ],
          "is_new": false,
          "appearance_count": 1,
          "time_info": "00时36分"
        },
        {
          "title": "美国总统特朗普：普尔特将短暂担任国家情报总监。",
          "url": "https://flash.jin10.com/detail/20260612041158684800",
          "source": "金十数据",
          "ranks": [
            22
          ],
          "is_new": false,
          "appearance_count": 1,
          "time_info": "05时35分"
        },
        {
          "title": "美债价格上涨、交易量激增，之前特朗普宣布取消对伊朗的打击计划",
          "url": "https://wallstreetcn.com/livenews/3118346",
          "source": "华尔街见闻-快讯",
          "ranks": [
            22
          ],
          "is_new": false,
          "appearance_count": 1,
          "time_info": "03时24分"
        },
        {
          "title": "美国总统特朗普：我们在这场对抗伊朗的战争中取得了军事胜利。",
          "url": "https://flash.jin10.com/detail/20260612040934547800",
          "source": "金十数据",
          "ranks": [
            23
          ],
          "is_new": false,
          "appearance_count": 1,
          "time_info": "05时35分"
        },
        {
          "title": "美国总统特朗普：伊朗人有机会重建他们的国家，伊朗已被严重摧毁。",
          "url": "https://flash.jin10.com/detail/20260612040929676800",
          "source": "金十数据",
          "ranks": [
            24
          ],
          "is_new": false,
          "appearance_count": 1,
          "time_info": "05时35分"
        },
        {
          "title": "分析人士：称特朗普声明并未改变局势",
          "url": "https://flash.jin10.com/detail/20260612023118594800",
          "source": "金十数据",
          "ranks": [
            25
          ],
          "is_new": false,
          "appearance_count": 1,
          "time_info": "03时24分"
        },
        {
          "title": "特朗普暗示协议即将达成，新兴市场货币与股票ETF集体大涨",
          "url": "https://wallstreetcn.com/livenews/3118418",
          "source": "华尔街见闻-快讯",
          "ranks": [
            25
          ],
          "is_new": true,
          "appearance_count": 1,
          "time_info": "07时11分"
        },
        {
          "title": "巴西雷亚尔兑美元涨1.4%，创最近两个月最佳盘中表现，美国总统特朗普取消打击伊朗的计划，称即将宣布签署协议的时间和地点。",
          "url": "https://wallstreetcn.com/livenews/3118342",
          "source": "华尔街见闻-快讯",
          "ranks": [
            26
          ],
          "is_new": false,
          "appearance_count": 1,
          "time_info": "03时24分"
        },
        {
          "title": "特朗普：取消了对伊朗的打击计划，海上封锁照旧",
          "url": "https://wallstreetcn.com/livenews/3118340",
          "source": "华尔街见闻-快讯",
          "ranks": [
            27
          ],
          "is_new": false,
          "appearance_count": 1,
          "time_info": "03时24分"
        },
        {
          "title": "特朗普：取消霍尔木兹海峡封锁是伊朗协议的一部分",
          "url": "https://wallstreetcn.com/livenews/3118386",
          "source": "华尔街见闻-快讯",
          "ranks": [
            27
          ],
          "is_new": false,
          "appearance_count": 1,
          "time_info": "05时35分"
        },
        {
          "title": "美债价格于纽约中午短线飙涨，特朗普宣称取消对伊朗的后续袭击计划",
          "url": "https://wallstreetcn.com/livenews/3118414",
          "source": "华尔街见闻-快讯",
          "ranks": [
            27
          ],
          "is_new": true,
          "appearance_count": 1,
          "time_info": "07时11分"
        },
        {
          "title": "伊朗国防部回应特朗普夺岛言论：敌人任何误判都将招致超乎想象的反击",
          "url": "https://wallstreetcn.com/livenews/3118338",
          "source": "华尔街见闻-快讯",
          "ranks": [
            29
          ],
          "is_new": false,
          "appearance_count": 1,
          "time_info": "03时24分"
        }
      ]
    },
    {
      "keyword_group": "美股 a股 港股",
      "match_count": 12,
      "titles": [
        {
          "title": "伊朗局势骤然升级，原油大涨，科技股抛售拖累美股，盘后甲骨文跳水9%，黄金暴跌",
          "url": "https://wallstreetcn.com/articles/3774300",
          "source": "华尔街见闻",
          "ranks": [
            1
          ],
          "is_new": false,
          "appearance_count": 4,
          "time_info": "[00时36分 ~ 07时11分]"
        },
        {
          "title": "六氟化钨概念爆火，A股多家上市公司回应相关业务情况",
          "url": "https://www.cls.cn/detail/2397515",
          "source": "财联社热门",
          "ranks": [
            1
          ],
          "is_new": false,
          "appearance_count": 4,
          "time_info": "[00时36分 ~ 07时11分]"
        },
        {
          "title": "特朗普威胁发动新袭击，美股高开，甲骨文跌12%，英特尔涨10%，油价走低，黄金重回4080美元",
          "url": "https://wallstreetcn.com/articles/3774389",
          "source": "华尔街见闻",
          "ranks": [
            5,
            4
          ],
          "is_new": false,
          "appearance_count": 3,
          "time_info": "[00时36分 ~ 05时35分]"
        },
        {
          "title": "A股上市公司批量调整锁价定增方案",
          "url": "https://wallstreetcn.com/livenews/3118445",
          "source": "华尔街见闻-快讯",
          "ranks": [
            1
          ],
          "is_new": true,
          "appearance_count": 1,
          "time_info": "07时11分"
        },
        {
          "title": "特朗普再次“TACO”，原油暴跌，美股债大反弹，半导体指数大涨8%，黄金收复4200关口",
          "url": "https://wallstreetcn.com/articles/3774389",
          "source": "华尔街见闻",
          "ranks": [
            4
          ],
          "is_new": true,
          "appearance_count": 1,
          "time_info": "07时11分"
        },
        {
          "title": "美股收盘：美伊局势反转纳指升超2.5% 芯片股强反弹费城指数涨8%",
          "url": "https://www.cls.cn/detail/2397755",
          "source": "财联社热门",
          "ranks": [
            4
          ],
          "is_new": true,
          "appearance_count": 1,
          "time_info": "07时11分"
        },
        {
          "title": "特朗普威胁“猛烈打击”伊朗 美股、原油市场反应温和 | 今夜看点",
          "url": "https://www.cls.cn/detail/2397555",
          "source": "财联社热门",
          "ranks": [
            7,
            8,
            9
          ],
          "is_new": false,
          "appearance_count": 4,
          "time_info": "[00时36分 ~ 07时11分]"
        },
        {
          "title": "美银：美股净抛售创纪录，科技板块外流达2008年以来最高",
          "url": "https://wallstreetcn.com/articles/3774357",
          "source": "华尔街见闻",
          "ranks": [
            9
          ],
          "is_new": false,
          "appearance_count": 1,
          "time_info": "00时36分"
        },
        {
          "title": "在美股时段交易的费城金银指数收涨5.40%，报328.19点。 在全球市场全天交易的纽约证交所ARCA金矿开采商指数涨4.01%，报2210.21点，美股开盘之前维持微幅下跌状态——持稳于2120点附近，随后微幅震荡上行，北京时间01:28开启一波瞬间加速上涨行情。 在美股时段交易的原材料指数收涨4.24%，报248.30点。 在美股时段交易的金属与矿业指数收涨6.02%，报301.05点，跳空高开之后持续上扬。",
          "url": "https://wallstreetcn.com/livenews/3118403",
          "source": "华尔街见闻-快讯",
          "ranks": [
            10
          ],
          "is_new": false,
          "appearance_count": 1,
          "time_info": "05时35分"
        },
        {
          "title": "美股大类资产类ETF多数收涨，新兴市场ETF涨约4.4%，黄金ETF涨超3.1%",
          "url": "https://wallstreetcn.com/livenews/3118395",
          "source": "华尔街见闻-快讯",
          "ranks": [
            18
          ],
          "is_new": false,
          "appearance_count": 1,
          "time_info": "05时35分"
        },
        {
          "title": "美满电子（迈威尔科技）美股盘后跌2%，该公司任命Dan Durn为首席财务官（CFO），6月15日生效。",
          "url": "https://wallstreetcn.com/livenews/3118391",
          "source": "华尔街见闻-快讯",
          "ranks": [
            22
          ],
          "is_new": false,
          "appearance_count": 1,
          "time_info": "05时35分"
        },
        {
          "title": "周四（6月11日），美股行业ETF普遍收涨，半导体ETF收涨6.75%，全球航空业ETF涨6.31%，全球科技股指数ETF、科技行业ETF、生物科技指数ETF、可选消费ETF、银行业ETF、网络股指数ETF至多涨3.73%，能源业ETF跌1.96%。",
          "url": "https://wallstreetcn.com/livenews/3118388",
          "source": "华尔街见闻-快讯",
          "ranks": [
            25
          ],
          "is_new": false,
          "appearance_count": 1,
          "time_info": "05时35分"
        }
      ]
    },
    {
      "keyword_group": "马斯克",
      "match_count": 3,
      "titles": [
        {
          "title": "特斯拉 FSD 中国山区挂壁公路实测爆火，马斯克转发，视频播放量破 4700 万，这种场景测试有多大参考意义？",
          "url": "https://www.zhihu.com/question/2048159787817375467",
          "source": "知乎",
          "ranks": [
            10,
            6,
            5
          ],
          "is_new": false,
          "appearance_count": 3,
          "time_info": "[03时24分 ~ 07时11分]"
        },
        {
          "title": "伊朗正在评估将马斯克旗下企业纳入军事目标清单，其中包括SpaceX",
          "url": "https://wallstreetcn.com/livenews/3118294",
          "source": "华尔街见闻-快讯",
          "ranks": [
            14
          ],
          "is_new": false,
          "appearance_count": 1,
          "time_info": "00时36分"
        },
        {
          "title": "Founders Fund（马斯克长期伙伴Peter Thiel主导的风投公司）与Andreessen Horowitz有望从SpaceX美国IPO获得创历史纪录的回报。（彭博）",
          "url": "https://wallstreetcn.com/livenews/3118397",
          "source": "华尔街见闻-快讯",
          "ranks": [
            16
          ],
          "is_new": false,
          "appearance_count": 1,
          "time_info": "05时35分"
        }
      ]
    },
    {
      "keyword_group": "半导体",
      "match_count": 3,
      "titles": [
        {
          "title": "【每日收评】创业板震荡调整跌超1%， 半导体材料持续爆发，小金属概念逆势活跃",
          "url": "https://www.cls.cn/detail/2397208",
          "source": "财联社热门",
          "ranks": [
            8,
            7
          ],
          "is_new": false,
          "appearance_count": 4,
          "time_info": "[00时36分 ~ 07时11分]"
        },
        {
          "title": "纳指涨幅达2％，道指涨1.6％，标普500指数涨1.3％。 费城半导体指数涨5.28%。",
          "url": "https://wallstreetcn.com/livenews/3118344",
          "source": "华尔街见闻-快讯",
          "ranks": [
            24
          ],
          "is_new": false,
          "appearance_count": 1,
          "time_info": "03时24分"
        },
        {
          "title": "纳斯达克金龙中国指数收涨0.25%，报6296.64点，北京时间01:28出现一波强势反弹行情——从6200点拉升大约60点。 热门中概股里，日月光半导体初步收涨7.2%，网易涨0.2%，阿里跌1.5%。 ETF中，MSCI新兴市场ex中国ETF（EMXC）收涨5.33%，XtrackersHarvest中证50（ASHS）收涨1.39%，德银嘉实沪深300指数ETF（ASHR）收涨1.04%。 中国科技指数ETF（CQQQ）收涨1.29%，中概互联网指数ETF（KWEB）收涨0.49%。",
          "url": "https://wallstreetcn.com/livenews/3118384",
          "source": "华尔街见闻-快讯",
          "ranks": [
            29
          ],
          "is_new": false,
          "appearance_count": 1,
          "time_info": "05时35分"
        }
      ]
    },
    {
      "keyword_group": "科创",
      "match_count": 1,
      "titles": [
        {
          "title": "【焦点复盘】科创50缩量收涨0.62%，AI上游涨价概念多点开花，机器人、物理AI板块遭重挫",
          "url": "https://www.cls.cn/detail/2397230",
          "source": "财联社热门",
          "ranks": [
            5,
            6,
            7
          ],
          "is_new": false,
          "appearance_count": 4,
          "time_info": "[00时36分 ~ 07时11分]"
        }
      ]
    },
    {
      "keyword_group": "商业航天",
      "match_count": 1,
      "titles": [
        {
          "title": "商业航天领域专家：2026年是中国火箭运力突破之年，相信短期内可以有大突破",
          "url": "https://wallstreetcn.com/livenews/3118431",
          "source": "华尔街见闻-快讯",
          "ranks": [
            14
          ],
          "is_new": true,
          "appearance_count": 1,
          "time_info": "07时11分"
        }
      ]
    },
    {
      "keyword_group": "宁德时代",
      "match_count": 1,
      "titles": [
        {
          "title": "独家|能源巨头战略延伸？宁德时代首次投资核聚变企业 为何“花落”贝塔聚变",
          "url": "https://www.cls.cn/detail/2397280",
          "source": "财联社热门",
          "ranks": [
            11,
            12,
            13
          ],
          "is_new": false,
          "appearance_count": 4,
          "time_info": "[00时36分 ~ 07时11分]"
        }
      ]
    }
  ],
  "report_image_url": "https://joyce677.github.io/TrendRadar/img/news.jpg"
}